lstm/__init__.py
lstm-0.1.0.dist-info/LICENSE
lstm-0.1.0.dist-info/METADATA
lstm-0.1.0.dist-info/WHEEL
lstm-0.1.0.dist-info/top_level.txt
lstm-0.1.0.dist-info/RECORD
