Metadata-Version: 2.1
Name: lstm
Version: 0.1.0
Summary: Pytorch implementation of LSTM variants
Home-page: https://github.com/astariul/lstm
Author: Nicolas REMOND
Author-email: remondnicola@gmail.com
License: UNKNOWN
Platform: UNKNOWN
Classifier: Programming Language :: Python :: 3.8
Classifier: Operating System :: OS Independent
Requires-Python: >=3.8
Provides-Extra: test
Provides-Extra: hook
Provides-Extra: lint
Provides-Extra: docs
Provides-Extra: all
Provides-Extra: dev
